{
    "pageSize": 10,
    "paging": {
        "enable": true,
        "settings": {
            "pageSizes": true,
            "pageSize": 20
        }
    },
    "sorting": {
        "enable": false
    },
    "grouping": {
        "enable": true,
        "group": []
    },
    "filtering": {
        "enable": true,
        "settings": {
            "type": "Menu"
        }
    },
    "formDialog": {
        "type": "sidebar",
        "closeAfterExecute": false,
        "size": "lg"
    },
    "customGrouping": false,
    "allowResizing": true,
    "reorderable": true,
    "selectable": true,
    "scrollable": false,
    "hideable": true,
    "refresh": false,
    "reset": true,
    "editSettings": {
        "allowEditing": true,
        "allowAdding": true,
        "allowDeleting": true,
        "showDeleteConfirmDialog": true,
        "mode": "Dialog"
    },
    "editSettingsRequest": {
        "add": {
            "type": "EMIT",
            "api": "/api/owner/setFishStocking",
            "parameters": [],
            "fields": "",
            "root": ""
        }
    },
    "columns": [
        {
            "className": "justify-content-center",
            "template": {
                "type": "inlineEditing"
            }
        },
        {
            "title": "commonFields.date",
            "filterable": true,
            "hideable": true,
            "filter": "date",
            "type": "string",
            "class": "text-align-right",
            "field": "date",
            "noEditable": true
        },
        {
            "title": "birdCount.heron",
            "filterable": true,
            "hideable": true,
            "filter": "date",
            "type": "string",
            "class": "text-align-right",
            "field": "heron"
        },
        {
            "title": "birdCount.cormorant",
            "filterable": true,
            "hideable": true,
            "filter": "date",
            "type": "string",
            "class": "text-align-right",
            "field": "cormorant"
        },
        {
            "title": "birdCount.gooseSayer",
            "filterable": true,
            "hideable": true,
            "filter": "date",
            "type": "string",
            "class": "text-align-right",
            "field": "goose_sayer"
        }
    ],
    "config": []
}